Workbook

Sheet 1. Parametros
A1: MODELO DE VIABILIDADE — PLATAFORMA DE INCLUSÃO ESCOLAR E CUIDADO CLÍNICO
A2: Município de referência: Guarujá/SP (IBGE 3518701)
A3: LEGENDA: células AMARELAS com texto AZUL são os parâmetros editáveis. Células pretas são fórmulas — não editar.
A4: Elaboração: G3 Health Service Ltda. — CNPJ 31.652.744/0001-14. Data-base: setembro de 2026.
A6: A. POPULAÇÃO-ALVO — CENSO 2022 (dado oficial, não editar)
A7: Faixa etária | B7: Pessoas com TEA em Guarujá | C7: Fonte
A8: 0 a 4 anos | B8: 579 | C8: IBGE, SIDRA 10145, var. 13267 — Censo 2022
A9: 5 a 9 anos | B9: 639 | C9: IBGE, SIDRA 10145, var. 13267 — Censo 2022
A10: 10 a 14 anos | B10: 518 | C10: IBGE, SIDRA 10145, var. 13267 — Censo 2022
A11: 15 a 19 anos | B11: 393 | C11: IBGE, SIDRA 10145, var. 13267 — Censo 2022
A12: Total 0 a 19 anos | B12: =SUM(B8:B11) -> 2129
A14: B. RECORTES ETÁRIOS ESTIMADOS (distribuição uniforme dentro da faixa)
A15: Recorte | B15: Fórmula aplicada | C15: Pessoas com TEA
A16: 4 a 18 anos (idade escolar ampla) | B16: 1/5 da faixa 0-4 + 5-9 + 10-14 + 4/5 da faixa 15-19 | C16: =ROUND(B8/5+B9+B10+B11*4/5,0) -> 1587
A17: 6 a 14 anos (Ensino Fundamental I e II) | B17: 4/5 da faixa 5-9 + 10-14 | C17: =ROUND(B9*4/5+B10,0) -> 1029
A19: C. PARÂMETROS DE COBERTURA (editáveis)
A20: Parâmetro | B20: Valor | C20: Observação
A21: % do público em rede pública municipal | B21: 0.6 | C21: A confirmar no Censo Escolar. Redes municipais de SP costumam concentrar EF I; EF II é frequentemente estadual.
A22: Fator de ampliação para demais públicos do AEE | B22: 1.6 | C22: TEA é apenas parte do público-alvo da educação especial. Fator 1,0 = só TEA. Calibrar pelo Censo Escolar local.
A23: Taxa de adesão efetiva ao programa | B23: 0.85 | C23: Nem todo elegível adere. Considera recusa familiar e perda de seguimento.
A24: % do público que recebe o pacote clínico | B24: 0.45 | C24: Parâmetro de política. Nem todo aluno com PEI demanda acompanhamento clínico intensivo.
A26: D. ESTRUTURA DA REDE (editáveis — confirmar no Censo Escolar)
A27: Parâmetro | B27: Valor | C27: Observação
A28: Unidades escolares da rede municipal | B28: 60 | C28: A CONFIRMAR. Valor provisório para fins de modelagem.
A29: Profissionais da educação a capacitar | B29: 900 | C29: A CONFIRMAR. Professores regentes, AEE, coordenação e gestão.
A30: Profissionais de saúde com acesso ao módulo | B30: 60 | C30: A CONFIRMAR. Rede municipal e conveniada que atende o público-alvo.
A31: Participantes por turma de formação | B31: 20 | C31: Limite pedagógico usual e adotado na ARP 045/2026 do CIMINAS.
A32: Horas de supervisão de casos por mês | B32: 40 | C32: Equipe multiprofissional. Dimensionar pelo número de casos complexos.
A34: E. FONTES E ÂNCORAS DE PREÇO PÚBLICO
A35: Referência | B35: Valor | C35: Origem
A36: Licença de plataforma de avaliação — aluno/ano | B36: 750.97 | C36: ARP 045/2026, CIMINAS, Item 1. Concorrência Eletrônica 004/2026.
A37: Implantação por unidade educacional | B37: 1162.49 | C37: ARP 045/2026, CIMINAS, Item 2.
A38: Formação — turma de até 20 profissionais | B38: 3520.84 | C38: ARP 045/2026, CIMINAS, Item 3.
A39: Locação de laboratório itinerante | B39: 2542.89 | C39: ARP 045/2026, CIMINAS, Item 4.
A40: Solução de AEE consorciada — valor global | B40: 1.1638924e+08 | C40: CIMPAR, Pregão Eletrônico 07/2026, homologado 16/07/2026. Vencedora: Cognvox.
A41: Sistema de gestão escolar municipal — rede inteira/ano | B41: 360000 | C41: Chorozinho/CE, processo 001-005/2026-AD-SEDUC, 12 meses.
A42: Licença privada de gestão de PEI — aluno/ano (inferido) | B42: 189 | C42: IncludED, plano intermediário no teto de 20 alunos. Cálculo aritmético, não preço publicado.

Sheet 2. Dimensionamento
A1: DIMENSIONAMENTO DO PÚBLICO — GUARUJÁ/SP
A2: Todos os valores derivam da aba 1. Alterar os parâmetros lá, não aqui.
A4: Etapa do dimensionamento | B4: Cálculo | C4: Alunos
A5: Pessoas com TEA de 4 a 18 anos (Censo 2022) | B5: =ROUND('1. Parametros'!C16,0) -> 1587 | C5: Base populacional oficial
A6: Em rede pública municipal | B6: =ROUND(B5*'1. Parametros'!$B$21,0) -> 952 | C6: Aplicado o percentual de rede
A7: Ampliado para o público-alvo do AEE | B7: =ROUND(B6*'1. Parametros'!$B$22,0) -> 1523 | C7: Inclui demais deficiências, TGD e altas habilidades
A8: Com adesão efetiva ao programa | B8: =ROUND(B7*'1. Parametros'!$B$23,0) -> 1295 | C8: PÚBLICO ATENDIDO PELA PLATAFORMA
A10: RECORTES COMPLEMENTARES
A11: Recorte | B11: Cálculo | C11: Alunos
A12: Público de Ensino Fundamental I e II (6 a 14 anos) | B12: =ROUND('1. Parametros'!C17*'1. Parametros'!$B$21*'1. Parametros'!$B$22*'1. Parametros'!$B$23,0) -> 840 | C12: Escopo da ARP 045/2026
A13: Público que recebe o pacote clínico | B13: =ROUND('2. Dimensionamento'!$B$8*'1. Parametros'!$B$24,0) -> 583 | C13: Aplica o percentual clínico da aba 1
A15: CONTEXTO ESTADUAL — CENSO 2022 (referência, não editar)
A16: Recorte | B16: Pessoas com TEA | C16: Observação
A17: Guarujá — 0 a 19 anos | B17: 2129 | C17: Município de referência deste estudo
A18: Estado de São Paulo — 0 a 19 anos | B18: 208381 | C18: 645 municípios
A19: Brasil — 0 a 19 anos | B19: 1060019 | C19: 5.570 municípios

Sheet 3. Plataforma
A1: CUSTO ANUAL DA SOLUÇÃO TECNOLÓGICA E DOS SERVIÇOS HABILITADORES
A2: Preços unitários em AMARELO são propostos e devem ser validados por pesquisa de preços (art. 23 da Lei 14.133/2021).
A4: Item | B4: Unidade | C4: Quantidade | D4: Preço unitário (R$) | E4: Total anual (R$) | F4: Âncora de preço
A5: Licença — Módulo Escola (governança e gestão de PEI) | B5: Unid. escolar/ano | C5: ='1. Parametros'!$B$28 -> 60 | D5: 6000 | E5: =C5*D5 -> 360000 | F5: Proposto. Sem referência pública direta; calibrar por pesquisa de preços.
A6: Licença — por educando com PEI ativo | B6: Aluno/ano | C6: ='2. Dimensionamento'!$B$8 -> 1295 | D6: 320 | E6: =C6*D6 -> 414400 | F6: Entre R$ 189 (privado, inferido) e R$ 750,97 (ARP 045/2026).
A7: Licença — Módulo Saúde | B7: Profissional/ano | C7: ='1. Parametros'!$B$30 -> 60 | D7: 900 | E7: =C7*D7 -> 54000 | F7: Proposto. Materializa a Lei 14.254/2021.
A8: Licença — Módulo Família | B8: Família/ano | C8: =ROUND('2. Dimensionamento'!$B$8*0.9,0) -> 1166 | D8: 60 | E8: =C8*D8 -> 69960 | F8: Proposto. Fator 0,9 por irmandade. Pode ser ofertado incluso.
A9: Painel de governança da Secretaria | B9: Licença/ano | C9: 1 | D9: 36000 | E9: =C9*D9 -> 36000 | F9: Proposto.
A10: Implantação e parametrização | B10: Serviço/unidade | C10: ='1. Parametros'!$B$28 -> 60 | D10: 1162.49 | E10: =C10*D10 -> 69749.4 | F10: ARP 045/2026, CIMINAS, Item 2 — referência pública direta.
A11: Migração e integração com sistemas legados | B11: Serviço/ponto | C11: 4 | D11: 28000 | E11: =C11*D11 -> 112000 | F11: Proposto. Educacenso/INEP, gestão escolar, sistemas de saúde.
A12: Formação continuada de profissionais | B12: Turma de até 20 | C12: =ROUNDUP('1. Parametros'!$B$29/'1. Parametros'!$B$31,0) -> 45 | D12: 3520.84 | E12: =C12*D12 -> 158437.8 | F12: ARP 045/2026, CIMINAS, Item 3 — referência pública direta.
A13: Supervisão e mentoria multiprofissional | B13: Hora técnica | C13: ='1. Parametros'!$B$32*12 -> 480 | D13: 240 | E13: =C13*D13 -> 115200 | F13: Proposto. Equipe com neuropediatra, TO e psicopedagogo.
A14: Suporte técnico, sustentação e evolução | B14: Mês | C14: 12 | D14: 9500 | E14: =C14*D14 -> 114000 | F14: Proposto. Aproximadamente 12% do licenciamento anual.
A15: TOTAL ANUAL — PLATAFORMA E SERVIÇOS | E15: =SUM(E5:E14) -> 1503747.2
A16: Custo por aluno atendido (R$/ano) | E16: =IFERROR('3. Plataforma'!$E$15/'2. Dimensionamento'!$B$8,0) -> 1161.1947
A18: MÓDULO OPCIONAL — AVALIAÇÃO PEDAGÓGICA GAMIFICADA (escopo da ARP 045/2026)
A19: Item | B19: Unidade | C19: Quantidade | D19: Preço unitário (R$) | E19: Total anual (R$) | F19: Âncora de preço
A20: Licença de plataforma de avaliação gamificada | B20: Aluno/ano | C20: ='2. Dimensionamento'!$B$8 -> 1295 | D20: 750.97 | E20: =C20*D20 -> 972506.15 | F20: ARP 045/2026, CIMINAS, Item 1 — referência pública direta.
A21: Locação de laboratório itinerante | B21: Serviço | C21: =ROUNDUP('1. Parametros'!$B$28/4,0) -> 15 | D21: 2542.89 | E21: =C21*D21 -> 38143.35 | F21: ARP 045/2026, CIMINAS, Item 4. Um laboratório para cada 4 unidades.
A22: TOTAL ANUAL — MÓDULO DE AVALIAÇÃO | E22: =SUM(E20:E21) -> 1010649.5

Sheet 4. Cuidado clinico
A1: CUSTO ANUAL DO CUIDADO CLÍNICO
A2: Valores unitários conforme tabela do contratante. Quantidades de fono, psicologia e psicopedagogia elevadas a 12 por ano a pedido do contratante.
A4: A. CUSTO POR ALUNO/ANO — PACOTE DE ATENDIMENTO PROFISSIONAL
A5: Serviço | B5: Valor por consulta (R$) | C5: Quantidade por ano | D5: Total por aluno/ano (R$) | E5: Observação técnica
A6: Consulta com neurologista | B6: 400 | C6: 3 | D6: =B6*C6 -> 1200 | E6: Presencial ou teleconsulta.
A7: Consulta com psiquiatra | B7: 400 | C7: 3 | D7: =B7*C7 -> 1200 | E7: Presencial ou teleconsulta.
A8: Fonoaudiologia | B8: 100 | C8: 12 | D8: =B8*C8 -> 1200 | E8: 12 sessões por ano equivalem a uma por mês. Referências clínicas para TEA frequentemente trabalham com periodicidade quinzenal ou semanal nas fases iniciais.
A9: Psicologia | B9: 150 | C9: 12 | D9: =B9*C9 -> 1800 | E9: Uma sessão por mês. Intervenções comportamentais estruturadas costumam exigir periodicidade maior nas fases iniciais.
A10: Psicopedagogia | B10: 100 | C10: 12 | D10: =B10*C10 -> 1200 | E10: Uma sessão por mês.
A11: TOTAL POR ALUNO/ANO | D11: =SUM(D6:D10) -> 6600
A12: Nota: medicação não integra este modelo. Ver aba 6.
A14: B. CUSTO AGREGADO PARA A REDE DE GUARUJÁ
A15: Componente | B15: Alunos | C15: Custo por aluno/ano (R$) | D15: Total anual (R$) | E15: Observação
A16: Atendimento profissional | B16: ='2. Dimensionamento'!$B$13 -> 583 | C16: ='4. Cuidado clinico'!$D$11 -> 6600 | D16: =B16*C16 -> 3847800 | E16: Aplica o percentual clínico definido na aba 1.
A17: TOTAL ANUAL — CUIDADO CLÍNICO | D17: =SUM(D16:D16) -> 3847800

Sheet 5. Consolidado
A1: CONSOLIDAÇÃO E CENÁRIOS — GUARUJÁ/SP
A3: Bloco | B3: Total anual (R$) | C3: % do programa | D3: Por aluno atendido (R$/ano)
A4: Plataforma, implantação, formação e suporte | B4: ='3. Plataforma'!$E$15 -> 1503747.2 | C4: =IFERROR(B4/$B$7,0) -> 0.2363566 | D4: =IFERROR(B4/'2. Dimensionamento'!$B$8,0) -> 1161.1947
A5: Módulo opcional de avaliação gamificada | B5: ='3. Plataforma'!$E$22 -> 1010649.5 | C5: =IFERROR(B5/$B$7,0) -> 0.15885229 | D5: =IFERROR(B5/'2. Dimensionamento'!$B$8,0) -> 780.42432
A6: Cuidado clínico — atendimento profissional | B6: ='4. Cuidado clinico'!$D$16 -> 3847800 | C6: =IFERROR(B6/$B$7,0) -> 0.60479111 | D6: =IFERROR(B6/'2. Dimensionamento'!$B$8,0) -> 2971.2741
A7: TOTAL DO PROGRAMA INTEGRAL | B7: =SUM(B4:B6) -> 6362196.7 | C7: =SUM(C4:C6) -> 1 | D7: =IFERROR(B7/'2. Dimensionamento'!$B$8,0) -> 4912.8932
A9: CENÁRIOS DE ESCOPO
A10: Cenário | B10: Composição | C10: Total anual (R$) | D10: Por aluno (R$/ano)
A11: A — Coordenação | B11: Somente plataforma de PEI, implantação, formação e suporte. Sem avaliação gamificada, sem cuidado clínico. | C11: ='3. Plataforma'!$E$15 -> 1503747.2 | D11: =IFERROR(C11/'2. Dimensionamento'!$B$8,0) -> 1161.1947
A12: B — Coordenação e avaliação | B12: Cenário A mais o módulo de avaliação gamificada e laboratórios. | C12: ='3. Plataforma'!$E$15+'3. Plataforma'!$E$22 -> 2514396.7 | D12: =IFERROR(C12/'2. Dimensionamento'!$B$8,0) -> 1941.6191
A13: C — Programa integral (recomendado) | B13: Cenário B mais o atendimento clínico profissional. É o desenho recomendado. | C13: ='3. Plataforma'!$E$15+'3. Plataforma'!$E$22+'4. Cuidado clinico'!$D$16 -> 6362196.7 | D13: =IFERROR(C13/'2. Dimensionamento'!$B$8,0) -> 4912.8932
A15: CONTRATO DE 5 ANOS (serviço contínuo, arts. 106 e 107 da Lei 14.133/2021)
A16: Cenário | B16: Ano 1 | C16: Anos 2 a 5 (cada) | D16: Total 5 anos
A17: A — Coordenação | B17: =C11 -> 1503747.2 | C17: =C11-'3. Plataforma'!$E$10-'3. Plataforma'!$E$11 -> 1321997.8 | D17: =B17+C17*4 -> 6791738.4
A18: B — Coordenação e avaliação | B18: =C12 -> 2514396.7 | C18: =C12-'3. Plataforma'!$E$10-'3. Plataforma'!$E$11 -> 2332647.3 | D18: =B18+C18*4 -> 11844986
A19: C — Programa integral (recomendado) | B19: =C13 -> 6362196.7 | C19: =C13-'3. Plataforma'!$E$10-'3. Plataforma'!$E$11 -> 6180447.3 | D19: =B19+C19*4 -> 31083986
A20: Nos anos 2 a 5 excluem-se implantação e integração, que são despesas não recorrentes. Valores a preços de 2026, sem reajuste.

Sheet 6. Canabidiol
A1: ANEXO — POR QUE A MEDICAÇÃO NÃO INTEGRA ESTE MODELO
A2: A rubrica de canabidiol foi retirada da equação. Esta aba registra a fundamentação técnica e jurídica da exclusão.
A4: Aspecto | B4: Situação | C4: Fonte
A5: Incorporação ao SUS para TEA | B5: NÃO INCORPORADO. O canabidiol não integra nenhuma lista oficial de medicamentos do SUS para transtorno do espectro autista. | C5: Notas técnicas NatJus/TJDFT e NAT/TRF2
A6: Avaliação pela CONITEC | B6: Avaliado para epilepsia refratária pediátrica, com recomendação DESFAVORÁVEL. A não incorporação foi formalizada pela Portaria SCTIE/MS nº 25, de 28/05/2021. Para TEA, análise de 2022 identificou um ensaio clínico e nove estudos observacionais e concluiu que os estudos são limitados para recomendar uso clínico. | C6: Portaria SCTIE/MS nº 25/2021; nota técnica NatJus
A7: Registro na ANVISA | B7: Os produtos usualmente prescritos são importados e NÃO POSSUEM REGISTRO na ANVISA. Não há preço CMED, o que impede a formação de preço de referência pelos mecanismos usuais. | C7: Notas técnicas NatJus/TJDFT
A8: Via de acesso | B8: Importação por pessoa física mediante autorização da ANVISA, nos termos da RDC nº 660/2022. A RDC nº 327 foi revisada em 28/01/2026; a via excepcional permanece, mas passou a ser tratada como transitória e sujeita a exigência reforçada de justificativa clínica. | C8: RDC ANVISA 660/2022; revisão da RDC 327 em 28/01/2026
A9: Prescrição médica | B9: A Resolução CFM nº 2.324/2022 autoriza a prescrição de canabidiol apenas para epilepsias da infância e adolescência refratárias — síndromes de Dravet, de Lennox-Gastaut e complexo de esclerose tuberosa — e veda a prescrição para indicações diversas. O TEA NÃO figura entre as indicações autorizadas. | C9: Resolução CFM nº 2.324/2022
A10: Estado da evidência | B10: Certeza BAIXA. Estudos majoritariamente observacionais, sem grupo controle, com dados subjetivos e alto risco de viés. A Sociedade Brasileira de Neurologia Infantil considera o uso no TEA experimental e sem garantia de eficácia. | C10: Revisões sistemáticas citadas nas notas NatJus; posição da SBNI
A11: Peso orçamentário evitado | B11: Na versão inicial do estudo a medicação representava R$ 4.760 por aluno ao ano, cerca de 42% do pacote clínico. Sua retirada reduz o custo e elimina o item de menor sustentação técnica do projeto. | C11: Cálculo sobre a tabela do contratante
A12: Risco para a Administração | B12: Contratar fornecimento de produto sem registro sanitário, fora de indicação autorizada pelo conselho profissional e não incorporado ao SUS expõe o gestor a questionamento dos órgãos de controle, a glosa e a responsabilização, além de criar precedente de difícil reversão. | C12: Análise G3
A14: RECOMENDAÇÃO
A15: — A rubrica de medicação foi retirada do objeto contratual. O cenário C da aba 5 é o desenho adotado.
A16: — Tratar o acesso ao canabidiol pela via individualizada já existente — avaliação clínica caso a caso, prescrição por médico habilitado e, quando cabível, autorização de importação pela ANVISA —, e não como item de fornecimento coletivo custeado por contrato de educação.
A17: — Se o município optar por instituir política própria de fornecimento, fazê-lo por lei municipal específica, com protocolo clínico, comissão de avaliação e rubrica orçamentária da Saúde, separada do contrato da plataforma.
A18: — Manter na plataforma o registro do uso de medicação prescrita, o que é função legítima de coordenação de cuidado e não implica custeio pelo contrato.

Sheet 7. Fontes
A1: FONTES, PREMISSAS E LIMITAÇÕES
A3: Item | B3: Conteúdo | C3: Natureza
A4: População com TEA | B4: IBGE, SIDRA tabela 10145, variável 13267 — Censo 2022, resultados preliminares da amostra. Pessoas com diagnóstico informado por profissional de saúde. Consulta em 29/09/2026. | C4: Dado oficial
A5: Recortes 4-18 e 6-14 | B5: Estimativa por distribuição uniforme dentro de cada faixa quinquenal. A tabela do IBGE não publica idade simples. | C5: Estimativa
A6: Âncoras de preço da plataforma | B6: ARP nº 045/2026 do CIMINAS, Concorrência Eletrônica nº 004/2026, assinada em 27/08/2026. | C6: Dado oficial
A7: Comparável público de AEE | B7: CIMPAR — Consórcio Intermunicipal Multifinalitário do Vale do Paraibuna. Pregão Eletrônico nº 07/2026, processo 09/2026, homologado em 16/07/2026. R$ 116.389.239,08. Vencedora: Cognvox. Quantidade de alunos e preço unitário não publicados. | C7: Dado público
A8: Sistema de gestão escolar municipal | B8: Chorozinho/CE, processo 001-005/2026-AD-SEDUC, R$ 360.000 por 12 meses. | C8: Dado público
A9: Preço privado de gestão de PEI | B9: IncludED — plano intermediário. Equivalência por aluno calculada no teto do plano; não é preço publicado por aluno. | C9: Inferência
A10: Valores de consulta e medicação | B10: Tabela fornecida pelo contratante em 29/09/2026. | C10: Informado pelo cliente
A11: Estrutura da rede de Guarujá | B11: Unidades escolares, profissionais e matrículas: PARÂMETROS PROVISÓRIOS. Devem ser substituídos pelos dados do Censo Escolar e da Secretaria Municipal de Educação antes de qualquer uso externo. | C11: A confirmar
A12: Preços unitários propostos | B12: Os itens sem âncora pública são propostos com base em prática de mercado e devem ser validados por pesquisa de preços nos termos do art. 23 da Lei nº 14.133/2021. | C12: A validar
A13: Regulação do canabidiol | B13: Portaria SCTIE/MS nº 25/2021; RDC ANVISA nº 660/2022; revisão da RDC nº 327 em 28/01/2026; Resolução CFM nº 2.324/2022; notas técnicas NatJus/TJDFT e NAT/TRF2. | C13: Dado oficial
